seedflow.py
seedflow-0.4.0.dist-info/LICENSE
seedflow-0.4.0.dist-info/METADATA
seedflow-0.4.0.dist-info/WHEEL
seedflow-0.4.0.dist-info/top_level.txt
seedflow-0.4.0.dist-info/RECORD
