Metadata-Version: 2.1
Name: seedflow
Version: 0.4.0
Summary: UNKNOWN
Home-page: UNKNOWN
License: MIT
Keywords: coroutines async side-effects data side-effects-as-data
Platform: UNKNOWN
Classifier: Development Status :: 3 - Alpha
Classifier: Intended Audience :: Developers
Classifier: License :: OSI Approved :: MIT License
Classifier: Programming Language :: Python :: 3
Classifier: Programming Language :: Python :: 3.7
Requires-Dist: din
Requires-Dist: rototiller
Requires-Dist: pipe
Provides-Extra: dev
Requires-Dist: ptpython ; extra == 'dev'
Provides-Extra: test
Requires-Dist: bandit ; extra == 'test'
Requires-Dist: better-exceptions ; extra == 'test'
Requires-Dist: blessed ; extra == 'test'
Requires-Dist: click ; extra == 'test'
Requires-Dist: coverage ; extra == 'test'
Requires-Dist: din ; extra == 'test'
Requires-Dist: flake8-assertive ; extra == 'test'
Requires-Dist: flake8-author ; extra == 'test'
Requires-Dist: flake8-blind-except ; extra == 'test'
Requires-Dist: flake8-bugbear ; extra == 'test'
Requires-Dist: flake8-builtins-unleashed ; extra == 'test'
Requires-Dist: flake8-commas ; extra == 'test'
Requires-Dist: flake8-comprehensions ; extra == 'test'
Requires-Dist: flake8-copyright ; extra == 'test'
Requires-Dist: flake8-debugger ; extra == 'test'
Requires-Dist: flake8-docstrings ; extra == 'test'
Requires-Dist: flake8-double-quotes ; extra == 'test'
Requires-Dist: flake8-expandtab ; extra == 'test'
Requires-Dist: flake8-imports ; extra == 'test'
Requires-Dist: flake8-mutable ; extra == 'test'
Requires-Dist: flake8-pep257 ; extra == 'test'
Requires-Dist: flake8-self ; extra == 'test'
Requires-Dist: flake8-single-quotes ; extra == 'test'
Requires-Dist: flake8-super-call ; extra == 'test'
Requires-Dist: flake8-tidy-imports ; extra == 'test'
Requires-Dist: flake8-todo ; extra == 'test'
Requires-Dist: flake8 ; extra == 'test'
Requires-Dist: mypy ; extra == 'test'
Requires-Dist: pylint ; extra == 'test'
Requires-Dist: pipe ; extra == 'test'
Requires-Dist: vulture ; extra == 'test'
